{
  "id": "trencar-la-mirada-adulta",
  "title": "Trencar la mirada adulta",
  "status": "published",
  "authors": [
    "lluisribes"
  ],
  "excerpt": "Un retrat d&#8217;en Lluís Raluy d&#8217;en Miquel Abat Gràcies Miquel per aquesta magnífica fotografia. Sencillament trenca la mirada adulta. La cuidaré! Aquesta fotografia és un retrat d&#8217;en Luis Raluy (http://luisraluy.com/) &nbsp;realitzat pel fotògraf Miquel Abat (http://melabat.blogspot.com.es/).\n",
  "categories": [
    "articulos"
  ],
  "tags": [],
  "publishedDate": "2013-09-02T21:16:00",
  "updatedAt": "2013-09-02T21:16:00",
  "wordpressId": 68
}