{
  "id": "dia-7-escocia",
  "title": "Escocia – Día 7",
  "status": "published",
  "authors": [
    "lluisribes"
  ],
  "excerpt": "Mostra un mapa més gran Una vez llegado al punto más al norte de Escocia, vuelvo hacia el sur pero por la otra costa, la costa este. El séptimo día lo planifico para realizar unas 150 millas, las que separa el norte de la ciudad de Inverness. Saliendo del hotel de Mey, me dirijo un &#8230; \nLlegir més&#8230;\n",
  "categories": [
    "escocia2008"
  ],
  "tags": [
    "canninch",
    "car",
    "coche",
    "comar lodge",
    "escocia",
    "inverness",
    "jonh o'groats",
    "lago ness",
    "loch mullardoch",
    "lybster",
    "scotland",
    "trip",
    "viaje"
  ],
  "publishedDate": "2008-11-02T14:13:00",
  "updatedAt": "2008-11-02T14:13:00",
  "wordpressId": 415
}