{
  "id": "fondo-documental-de-fotos",
  "title": "Fondo documental de fotos",
  "status": "published",
  "authors": [
    "lluisribes"
  ],
  "excerpt": "Alguna vez os he hablado de flickr, un lugar en la web donde compartir tus fotografias. Una de las posibilidades que te da es la crear grupos, donde otros usuarios pueden participar subiendo fotos y comentarios. Normalmente los grupos se crean alrededor de una temática y con unas reglas básicas que el administrador o administradores &#8230; \nLlegir més&#8230;\n",
  "categories": [
    "articulos"
  ],
  "tags": [
    "barcelona",
    "flickr",
    "fotos",
    "girona",
    "lleida",
    "red social",
    "social network",
    "tarragona",
    "tune"
  ],
  "publishedDate": "2007-01-07T12:59:00",
  "updatedAt": "2007-01-07T12:59:00",
  "wordpressId": 503
}