{
  "id": "carta-a-potos",
  "title": "Carta a Potos",
  "status": "published",
  "authors": [
    "lluisribes"
  ],
  "excerpt": "&#8220;Potos&#8221; &#8211; Lluís Ribes i Portillo (cc) &#8220;Estic tancat en un record gris i fred que deixa la meva pell constantment humida.   Si m&#8217;aguaito, ploro. Si em recullo de què em protegeixes?   De viure!   Vull sentir el dolorós corrent del meu centre a l&#8217;oblit de la terra.   I un cop fora ballar sota &#8230; \nLlegir més&#8230;\n",
  "categories": [
    "articulos",
    "fotografia",
    "poemes"
  ],
  "tags": [
    "Lluís Ribes i Portillo",
    "poema",
    "poesia",
    "potos"
  ],
  "publishedDate": "2014-11-14T00:12:00",
  "updatedAt": "2020-12-08T14:22:06",
  "wordpressId": 3853
}