{
  "id": "httplluisribes-googlepages-com",
  "title": "http://lluisribes.googlepages.com",
  "status": "published",
  "authors": [
    "lluisribes"
  ],
  "excerpt": "Nueva versión de mi página web. He cambiado mi foto tomando el sol en las playas Argentinas por una de más familiar de estas fechas navideñas. También he añadido un par de &#8220;gadgets&#8221;, una nueva opción de Google Pages.La URL de la web es la siguiente: http://lluisribes.googlepages.com\n",
  "categories": [
    "articulos"
  ],
  "tags": [
    "google",
    "googlepages",
    "Lluís Ribes",
    "personal",
    "web"
  ],
  "publishedDate": "2007-01-15T22:01:00",
  "updatedAt": "2007-01-15T22:01:00",
  "wordpressId": 502
}