{
  "id": "amor-portaves-al-mon",
  "title": "Amor, portaves al món…",
  "status": "published",
  "authors": [
    "lluisribes"
  ],
  "excerpt": "&nbsp; &#8220;Amor, portaves al món set mil set-cents seixanta-cinc dies, en cloure&#8217;s la nit que em vas cridar del teu racó, veu que s&#8217;havia compadit i em rebies, cos bondadós. Quin joc perdut, quin rodar fins a trencar un brancam fosc. Set mil set-cents seixanta-cinc dies, abans no vaig trobar on te havies arraulit, amor, &#8230; \nLlegir més&#8230;\n",
  "categories": [
    "fotos"
  ],
  "tags": [
    "amor",
    "Gabriel Ferrater",
    "poesia"
  ],
  "publishedDate": "2015-02-13T22:42:00",
  "updatedAt": "2015-02-13T22:42:00",
  "wordpressId": 2800
}