{
  "id": "311",
  "title": "Hola de nuevo, desde el hángar",
  "status": "published",
  "authors": [
    "lluisribes"
  ],
  "excerpt": "Hola de nuevo, os vuelvo a escribir, ahora desde el aeropuerto de Las Vegas (01:00 am) una vez terminado el taller de fotografía en Death Valley. Hemos estado los dos últimos días recorriendo mucho en coche y es que es lo que tiene el parque, que las distancias no son pequeñas. Os resumo, desde els &#8230; \nLlegir més&#8230;\n",
  "categories": [
    "death-valley-lone-pine"
  ],
  "tags": [],
  "publishedDate": "2010-03-29T07:39:00",
  "updatedAt": "2010-03-29T07:39:00",
  "wordpressId": 311
}