{
  "id": "firma",
  "title": "Firma",
  "status": "published",
  "authors": [
    "lluisribes"
  ],
  "excerpt": "Son tan solo 30 segundos, haz click en la siguiente imagen y actúa: Parisa, Iran, Khayrieh, Shamameh, Kobra, Soghra y Fatemeh son siete mujeres iraníes condenadas a morir lapidadas. Firma ahora para intentar salvarlas. http://www.es.amnesty.org/actua\n",
  "categories": [
    "articulos"
  ],
  "tags": [],
  "publishedDate": "2006-10-25T19:41:00",
  "updatedAt": "2006-10-25T19:41:00",
  "wordpressId": 524
}